setup.py
wtafinance/__init__.py
wtafinance/settings.py
wtafinance.egg-info/PKG-INFO
wtafinance.egg-info/SOURCES.txt
wtafinance.egg-info/dependency_links.txt
wtafinance.egg-info/top_level.txt
wtafinance/finance_api/__init__.py
wtafinance/finance_api/filedata_source_process.py
wtafinance/finance_api/stock.py
wtafinance/stock/__init__.py
wtafinance/stock/wta_data.py
wtafinance/tools/__init__.py
wtafinance/tools/data_visualization.py
wtafinance/tools/mongodb_helper.py
wtafinance/tools/tongdaxun_pojie.py
wtafinance/wtastock/__init__.py