Metadata-Version: 1.0
Name: wtafinance
Version: 1.0.14
Summary: This is wtafinance of the setup
Home-page: https://github.com/YIRanTang/wtafinance
Author: tby
Author-email: 1049268431@qq.com
License: UNKNOWN
Platform: UNKNOWN
